{"id":"1534","uri":"/selfcnil/api/configuration/site/document/1534/content","contents":[{"locale":"fr_FR","content":"<p>Le montant d'une amende est déterminé par la <a href=\"https://www.cnil.fr/cnil-direct/question/sanctions-quelles-sont-les-etapes-de-la-procedure-de-sanction-la-cnil?visiteur=pro\" target=\"_blank\">formation restreinte</a> de la CNIL <strong>au cas par cas</strong> en tenant compte, notamment :</p>\r\n\r\n<ul>\r\n\t<li>De&nbsp; la nature ou de la gravité du manquement.</li>\r\n\t<li>Du nombre de personnes concernées par le fichier.</li>\r\n\t<li>Du fait que la violation a été commise délibérément ou par simple négligence.</li>\r\n\t<li>Des catégories de données concernées.</li>\r\n\t<li>De la taille et de la situation financière de l'organisme dans la mesure où le montant de l'amende doit être proportionné.&nbsp;</li>\r\n</ul>\r\n\r\n<p><strong><span style=\"color:#ff5122;\">En savoir plus :</span></strong> <a href=\"https://www.cnil.fr/fr/les-etapes-de-la-procedure-de-sanction\" target=\"_top\">Les étapes de la procédure de sanction</a>&nbsp;</p>\r\n","format":"text/html"}]}