{"id":"186","uri":"/selfcnil/api/configuration/site/document/186","names":[{"name":"Démarchage par courriel vocal : conseils et recours.","locale":"fr_FR"}],"metadata":[{"locale":"fr_FR","name":"description","property":null,"content":"spam, appel, téléphone, mobile, portable, smartphone, sms, mms, mél, email, 33700, pingcall"}],"content":{"uri":"/selfcnil/api/configuration/site/document/186/content"},"creator":{"uri":"/selfcnil/api/configuration/site/document/186/creator"},"creationDate":1425310922000,"lastModifier":{"uri":"/selfcnil/api/configuration/site/document/186/lastModifier"},"lastModificationDate":1441643503000,"fields":[{"name":"Description","value":null,"fieldType":"TEXT","fieldOrder":null,"fieldLength":null,"listOfValueId":null,"visibleByAgent":null,"visibleBySupervisor":null,"visibleByExternalSpecialist":null,"mandatoryForAgent":null,"mandatoryForSupervisor":null,"readonlyForAgent":null,"readonlyForSupervisor":null,"localisation":[{"label":"Description","value":"spam, appel, téléphone, mobile, portable, smartphone, sms, mms, mél, email, 33700, pingcall","locale":"fr_FR"}]},{"name":"OrderTemplate","value":"","fieldType":"STRING","fieldOrder":null,"fieldLength":null,"listOfValueId":null,"visibleByAgent":null,"visibleBySupervisor":null,"visibleByExternalSpecialist":null,"mandatoryForAgent":null,"mandatoryForSupervisor":null,"readonlyForAgent":null,"readonlyForSupervisor":null,"localisation":[{"label":"Ordre d'affichage","value":"","locale":"fr_FR"}]}],"hits":[{"locale":"fr_FR","hits":119}],"ranks":[{"locale":"fr_FR","rank":1.411764705882353,"count":68}],"contacts":{"uri":"/selfcnil/api/configuration/site/document/186/contacts"},"relatedDocuments":{"uri":"/selfcnil/api/configuration/site/document/186/relatedDocuments"},"attachments":{"uri":"/selfcnil/api/configuration/site/document/186/attachments"},"path":[{"id":"12","uri":"/selfcnil/api/configuration/site/documentGroup/12"},{"id":"65","uri":"/selfcnil/api/configuration/site/documentGroup/65"},{"id":"85","uri":"/selfcnil/api/configuration/site/documentGroup/85"}],"parentGroup":{"id":"85","uri":"/selfcnil/api/configuration/site/documentGroup/85"},"publicationStatus":"None"}